mess_server/__init__.py
mess_server/server.py
mess_server/common/__init__.py
mess_server/common/decos.py
mess_server/common/descryptors.py
mess_server/common/errors.py
mess_server/common/metaclasses.py
mess_server/common/utils.py
mess_server/common/variables.py
mess_server/logs/__init__.py
mess_server/logs/config_client_log.py
mess_server/logs/config_server_log.py
mess_server/server/__init__.py
mess_server/server/add_user.py
mess_server/server/config_window.py
mess_server/server/core.py
mess_server/server/database.py
mess_server/server/main_window.py
mess_server/server/remove_user.py
mess_server/server/stat_window.py
mess_server/unit_tests/__init__.py
mess_server/unit_tests/test_client.py
mess_server/unit_tests/test_utils.py
vitalijtverskoj_mess_server-0.2.dist-info/LICENSE.txt
vitalijtverskoj_mess_server-0.2.dist-info/METADATA
vitalijtverskoj_mess_server-0.2.dist-info/WHEEL
vitalijtverskoj_mess_server-0.2.dist-info/top_level.txt
vitalijtverskoj_mess_server-0.2.dist-info/RECORD
