Metadata-Version: 2.1
Name: vitalijtverskoj-mess-server
Version: 0.2
Summary: Server packet
Author: Geek Brains
Author-email: gb@gb.ru
License-File: LICENSE.txt
